toaztr_specs/__init__.py
toaztr_specs/toaztr.json
toaztr_specs-0.110.0.dist-info/METADATA
toaztr_specs-0.110.0.dist-info/WHEEL
toaztr_specs-0.110.0.dist-info/top_level.txt
toaztr_specs-0.110.0.dist-info/RECORD
