Metadata-Version: 2.1
Name: toaztr-specs
Version: 0.110.0
Summary: OpenAPI specs of Toaztr
Home-page: https://github.com/Toaztr/specs
Author: Toaztr SAS
Project-URL: Bug Tracker, https://github.com/Toaztr/specs/issues
Classifier: Programming Language :: Python :: 3
Classifier: License :: OSI Approved :: MIT License
Classifier: Operating System :: OS Independent
